brip/__init__.py
brip/brip.py
brython_brip-0.1.0.dist-info/LICENSE
brython_brip-0.1.0.dist-info/METADATA
brython_brip-0.1.0.dist-info/WHEEL
brython_brip-0.1.0.dist-info/entry_points.txt
brython_brip-0.1.0.dist-info/top_level.txt
brython_brip-0.1.0.dist-info/RECORD
