Metadata-Version: 2.1
Name: brython-brip
Version: 0.1.0
Summary: brip stands for Brython's pip. It brings the Python Package Index (PyPI) ecosystem and the pip-like workflow to Brython-powered project.
Home-page: https://github.com/rayluo/brip
Author: Ray Luo
Author-email: rayluo.mba@gmail.com
License: MIT
Project-URL: Changelog, https://github.com/rayluo/brip/releases
Keywords: pip,brython,package,install
Platform: UNKNOWN
Classifier: Development Status :: 4 - Beta
Classifier: Intended Audience :: Developers
Classifier: License :: OSI Approved :: MIT License
Classifier: Topic :: Software Development :: Build Tools
Classifier: Operating System :: OS Independent
Classifier: Programming Language :: Python
Classifier: Programming Language :: Python :: 3
Classifier: Programming Language :: Python :: 3.6
Classifier: Programming Language :: Python :: 3.7
Classifier: Programming Language :: Python :: 3.8
Classifier: Programming Language :: Python :: 3.9
Requires-Dist: brython (<4,>=3.9)
Requires-Dist: pip
